
    <text
       x="23.264047611376554"
       y="548"
       id="text10001"
       xml:space="preserve"
       style="font-style:normal;font-variant:normal;font-weight:normal;font-stretch:normal;line-height:0%;font-family:Arial;-inkscape-font-specification:'Arial, Normal';text-align:start;writing-mode:lr-tb;text-anchor:start;fill:#000000;fill-opacity:1"
       inkscape:label="Johannes Oecolampadius (1482-1531)"><tspan
         sodipodi:role="line"
         id="tspan10001"
         x="23.264047611376554"
         y="553"
         style="font-size:13px;line-height:1.25">Johannes Oecolampadius (1482-1531)</tspan></text>
    <text
       x="23.264047611376554"
       y="578"
       id="text10002"
       xml:space="preserve"
       style="font-style:normal;font-variant:normal;font-weight:normal;font-stretch:normal;line-height:0%;font-family:Arial;-inkscape-font-specification:'Arial, Normal';text-align:start;writing-mode:lr-tb;text-anchor:start;fill:#000000;fill-opacity:1"
       inkscape:label="Huldrych Zwingli (1484-1531)"><tspan
         sodipodi:role="line"
         id="tspan10002"
         x="23.264047611376554"
         y="583"
         style="font-size:13px;line-height:1.25">Huldrych Zwingli (1484-1531)</tspan></text>
    <text
       x="23.264047611376554"
       y="608"
       id="text10003"
       xml:space="preserve"
       style="font-style:normal;font-variant:normal;font-weight:normal;font-stretch:normal;line-height:0%;font-family:Arial;-inkscape-font-specification:'Arial, Normal';text-align:start;writing-mode:lr-tb;text-anchor:start;fill:#000000;fill-opacity:1"
       inkscape:label="William Farel (1489-1565)"><tspan
         sodipodi:role="line"
         id="tspan10003"
         x="23.264047611376554"
         y="613"
         style="font-size:13px;line-height:1.25">William Farel (1489-1565)</tspan></text>
    <text
       x="23.264047611376554"
       y="638"
       id="text10004"
       xml:space="preserve"
       style="font-style:normal;font-variant:normal;font-weight:normal;font-stretch:normal;line-height:0%;font-family:Arial;-inkscape-font-specification:'Arial, Normal';text-align:start;writing-mode:lr-tb;text-anchor:start;fill:#000000;fill-opacity:1"
       inkscape:label="Martin Bucer (1491-1551)"><tspan
         sodipodi:role="line"
         id="tspan10004"
         x="23.264047611376554"
         y="643"
         style="font-size:13px;line-height:1.25">Martin Bucer (1491-1551)</tspan></text>
    <text
       x="23.264047611376554"
       y="668"
       id="text10005"
       xml:space="preserve"
       style="font-style:normal;font-variant:normal;font-weight:normal;font-stretch:normal;line-height:0%;font-family:Arial;-inkscape-font-specification:'Arial, Normal';text-align:start;writing-mode:lr-tb;text-anchor:start;fill:#000000;fill-opacity:1"
       inkscape:label="Peter Martyr Vermigli (1499-1562)"><tspan
         sodipodi:role="line"
         id="tspan10005"
         x="23.264047611376554"
         y="673"
         style="font-size:13px;line-height:1.25">Peter Martyr Vermigli (1499-1562)</tspan></text>
    <text
       x="29.26694818292799"
       y="698"
       id="text10006"
       xml:space="preserve"
       style="font-style:normal;font-variant:normal;font-weight:normal;font-stretch:normal;line-height:0%;font-family:Arial;-inkscape-font-specification:'Arial, Normal';text-align:start;writing-mode:lr-tb;text-anchor:start;fill:#000000;fill-opacity:1"
       inkscape:label="Heinrich Bullinger (1504-1575)"><tspan
         sodipodi:role="line"
         id="tspan10006"
         x="29.26694818292799"
         y="703"
         style="font-size:13px;line-height:1.25">Heinrich Bullinger (1504-1575)</tspan></text>
    <text
       x="36.770573897367285"
       y="728"
       id="text10007"
       xml:space="preserve"
       style="font-style:normal;font-variant:normal;font-weight:normal;font-stretch:normal;line-height:0%;font-family:Arial;-inkscape-font-specification:'Arial, Normal';text-align:start;writing-mode:lr-tb;text-anchor:start;fill:#000000;fill-opacity:1"
       inkscape:label="John Calvin (1509-1564)"><tspan
         sodipodi:role="line"
         id="tspan10007"
         x="36.770573897367285"
         y="733"
         style="font-size:13px;line-height:1.25">John Calvin (1509-1564)</tspan></text>
    <text
       x="44.274199611806125"
       y="758"
       id="text10008"
       xml:space="preserve"
       style="font-style:normal;font-variant:normal;font-weight:normal;font-stretch:normal;line-height:0%;font-family:Arial;-inkscape-font-specification:'Arial, Normal';text-align:start;writing-mode:lr-tb;text-anchor:start;fill:#000000;fill-opacity:1"
       inkscape:label="John Knox (1514-1572)"><tspan
         sodipodi:role="line"
         id="tspan10008"
         x="44.274199611806125"
         y="763"
         style="font-size:13px;line-height:1.25">John Knox (1514-1572)</tspan></text>
    <text
       x="51.77782532624542"
       y="788"
       id="text10009"
       xml:space="preserve"
       style="font-style:normal;font-variant:normal;font-weight:normal;font-stretch:normal;line-height:0%;font-family:Arial;-inkscape-font-specification:'Arial, Normal';text-align:start;writing-mode:lr-tb;text-anchor:start;fill:#000000;fill-opacity:1"
       inkscape:label="Theodore Beza (1519-1605)"><tspan
         sodipodi:role="line"
         id="tspan10009"
         x="51.77782532624542"
         y="793"
         style="font-size:13px;line-height:1.25">Theodore Beza (1519-1605)</tspan></text>
    <text
       x="529.0084207645741"
       y="818"
       id="text10010"
       xml:space="preserve"
       style="font-style:normal;font-variant:normal;font-weight:normal;font-stretch:normal;line-height:0%;font-family:Arial;-inkscape-font-specification:'Arial, Normal';text-align:start;writing-mode:lr-tb;text-anchor:start;fill:#000000;fill-opacity:1"
       inkscape:label="Abraham Kuyper (1837-1920)"><tspan
         sodipodi:role="line"
         id="tspan10010"
         x="529.0084207645741"
         y="823"
         style="font-size:13px;line-height:1.25">Abraham Kuyper (1837-1920)</tspan></text>
    <text
       x="550.0185727650037"
       y="848"
       id="text10011"
       xml:space="preserve"
       style="font-style:normal;font-variant:normal;font-weight:normal;font-stretch:normal;line-height:0%;font-family:Arial;-inkscape-font-specification:'Arial, Normal';text-align:start;writing-mode:lr-tb;text-anchor:start;fill:#000000;fill-opacity:1"
       inkscape:label="B. B. Warfield (1851-1921)"><tspan
         sodipodi:role="line"
         id="tspan10011"
         x="550.0185727650037"
         y="853"
         style="font-size:13px;line-height:1.25">B. B. Warfield (1851-1921)</tspan></text>
    <text
       x="554.5207481936668"
       y="878"
       id="text10012"
       xml:space="preserve"
       style="font-style:normal;font-variant:normal;font-weight:normal;font-stretch:normal;line-height:0%;font-family:Arial;-inkscape-font-specification:'Arial, Normal';text-align:start;writing-mode:lr-tb;text-anchor:start;fill:#000000;fill-opacity:1"
       inkscape:label="Herman Bavinck (1854-1921)"><tspan
         sodipodi:role="line"
         id="tspan10012"
         x="554.5207481936668"
         y="883"
         style="font-size:13px;line-height:1.25">Herman Bavinck (1854-1921)</tspan></text>
    <text
       x="595.0403270516381"
       y="908"
       id="text10013"
       xml:space="preserve"
       style="font-style:normal;font-variant:normal;font-weight:normal;font-stretch:normal;line-height:0%;font-family:Arial;-inkscape-font-specification:'Arial, Normal';text-align:start;writing-mode:lr-tb;text-anchor:start;fill:#000000;fill-opacity:1"
       inkscape:label="J. Gresham Machen (1881-1937)"><tspan
         sodipodi:role="line"
         id="tspan10013"
         x="595.0403270516381"
         y="913"
         style="font-size:13px;line-height:1.25">J. Gresham Machen (1881-1937)</tspan></text>
    <text
       x="602.5439527660774"
       y="938"
       id="text10014"
       xml:space="preserve"
       style="font-style:normal;font-variant:normal;font-weight:normal;font-stretch:normal;line-height:0%;font-family:Arial;-inkscape-font-specification:'Arial, Normal';text-align:start;writing-mode:lr-tb;text-anchor:start;fill:#000000;fill-opacity:1"
       inkscape:label="Karl Barth (1886-1968)"><tspan
         sodipodi:role="line"
         id="tspan10014"
         x="602.5439527660774"
         y="943"
         style="font-size:13px;line-height:1.25">Karl Barth (1886-1968)</tspan></text>
    <text
       x="616.0504790520677"
       y="968"
       id="text10015"
       xml:space="preserve"
       style="font-style:normal;font-variant:normal;font-weight:normal;font-stretch:normal;line-height:0%;font-family:Arial;-inkscape-font-specification:'Arial, Normal';text-align:start;writing-mode:lr-tb;text-anchor:start;fill:#000000;fill-opacity:1"
       inkscape:label="Cornelius Van Til (1895-1987)"><tspan
         sodipodi:role="line"
         id="tspan10015"
         x="616.0504790520677"
         y="973"
         style="font-size:13px;line-height:1.25">Cornelius Van Til (1895-1987)</tspan></text>
    <text
       x="622.0533796236191"
       y="998"
       id="text10016"
       xml:space="preserve"
       style="font-style:normal;font-variant:normal;font-weight:normal;font-stretch:normal;line-height:0%;font-family:Arial;-inkscape-font-specification:'Arial, Normal';text-align:start;writing-mode:lr-tb;text-anchor:start;fill:#000000;fill-opacity:1"
       inkscape:label="Martyn Lloyd-Jones (1899-1981)"><tspan
         sodipodi:role="line"
         id="tspan10016"
         x="622.0533796236191"
         y="1003"
         style="font-size:13px;line-height:1.25">Martyn Lloyd-Jones (1899-1981)</tspan></text>
    <text
       x="626.5555550522827"
       y="1028"
       id="text10017"
       xml:space="preserve"
       style="font-style:normal;font-variant:normal;font-weight:normal;font-stretch:normal;line-height:0%;font-family:Arial;-inkscape-font-specification:'Arial, Normal';text-align:start;writing-mode:lr-tb;text-anchor:start;fill:#000000;fill-opacity:1"
       inkscape:label="Gordon Clark (1902-1985)"><tspan
         sodipodi:role="line"
         id="tspan10017"
         x="626.5555550522827"
         y="1033"
         style="font-size:13px;line-height:1.25">Gordon Clark (1902-1985)</tspan></text>
    <text
       x="662.5729584815904"
       y="1058"
       id="text10018"
       xml:space="preserve"
       style="font-style:normal;font-variant:normal;font-weight:normal;font-stretch:normal;line-height:0%;font-family:Arial;-inkscape-font-specification:'Arial, Normal';text-align:start;writing-mode:lr-tb;text-anchor:start;fill:#000000;fill-opacity:1"
       inkscape:label="J. I. Packer (1926-present)"><tspan
         sodipodi:role="line"
         id="tspan10018"
         x="662.5729584815904"
         y="1063"
         style="font-size:13px;line-height:1.25">J. I. Packer (1926-present)</tspan></text>
    <text
       x="682.0823853391321"
       y="1088"
       id="text10019"
       xml:space="preserve"
       style="font-style:normal;font-variant:normal;font-weight:normal;font-stretch:normal;line-height:0%;font-family:Arial;-inkscape-font-specification:'Arial, Normal';text-align:start;writing-mode:lr-tb;text-anchor:start;fill:#000000;fill-opacity:1"
       inkscape:label="R. C. Sproul (1939-2017)"><tspan
         sodipodi:role="line"
         id="tspan10019"
         x="682.0823853391321"
         y="1093"
         style="font-size:13px;line-height:1.25">R. C. Sproul (1939-2017)</tspan></text>
    <text
       x="682.0823853391321"
       y="1118"
       id="text10020"
       xml:space="preserve"
       style="font-style:normal;font-variant:normal;font-weight:normal;font-stretch:normal;line-height:0%;font-family:Arial;-inkscape-font-specification:'Arial, Normal';text-align:start;writing-mode:lr-tb;text-anchor:start;fill:#000000;fill-opacity:1"
       inkscape:label="John F. MacArthur (1939-present)"><tspan
         sodipodi:role="line"
         id="tspan10020"
         x="682.0823853391321"
         y="1123"
         style="font-size:13px;line-height:1.25">John F. MacArthur (1939-present)</tspan></text>
    <text
       x="682.0823853391321"
       y="1148"
       id="text10021"
       xml:space="preserve"
       style="font-style:normal;font-variant:normal;font-weight:normal;font-stretch:normal;line-height:0%;font-family:Arial;-inkscape-font-specification:'Arial, Normal';text-align:start;writing-mode:lr-tb;text-anchor:start;fill:#000000;fill-opacity:1"
       inkscape:label="David F. Wells (1939-present)"><tspan
         sodipodi:role="line"
         id="tspan10021"
         x="682.0823853391321"
         y="1153"
         style="font-size:13px;line-height:1.25">David F. Wells (1939-present)</tspan></text>
    <text
       x="698.5903619108981"
       y="1178"
       id="text10022"
       xml:space="preserve"
       style="font-style:normal;font-variant:normal;font-weight:normal;font-stretch:normal;line-height:0%;font-family:Arial;-inkscape-font-specification:'Arial, Normal';text-align:start;writing-mode:lr-tb;text-anchor:start;fill:#000000;fill-opacity:1"
       inkscape:label="Timothy J. Keller (1950-present)"><tspan
         sodipodi:role="line"
         id="tspan10022"
         x="698.5903619108981"
         y="1183"
         style="font-size:13px;line-height:1.25">Timothy J. Keller (1950-present)</tspan></text>
    <text
       x="719.6005139113277"
       y="1208"
       id="text10023"
       xml:space="preserve"
       style="font-style:normal;font-variant:normal;font-weight:normal;font-stretch:normal;line-height:0%;font-family:Arial;-inkscape-font-specification:'Arial, Normal';text-align:start;writing-mode:lr-tb;text-anchor:start;fill:#000000;fill-opacity:1"
       inkscape:label="Michael Horton (theologian) (1964-present)"><tspan
         sodipodi:role="line"
         id="tspan10023"
         x="719.6005139113277"
         y="1213"
         style="font-size:13px;line-height:1.25">Michael Horton (theologian) (1964-present)</tspan></text>
